rsc_on_this_day-0.4.0.dist-info/METADATA
rsc_on_this_day-0.4.0.dist-info/top_level.txt
rsc_on_this_day-0.4.0.dist-info/WHEEL
rsc_on_this_day-0.4.0.dist-info/LICENSE
rsc_on_this_day-0.4.0.dist-info/entry_points.txt
rsc_on_this_day/__init__.py
rsc_on_this_day/__main__.py
rsc_on_this_day-0.4.0.dist-info/RECORD
