Metadata-Version: 2.1
Name: rsc-on-this-day
Version: 0.4.0
Summary: Displays Royal Society of Chemistry "On This Day" facts.
Author-email: Dominic Davis-Foster <dominic@davis-foster.co.uk>
License: MIT
Keywords: chemistry,terminal
Home-page: https://github.com/domdfcoding/rsc-on-this-day
Project-URL: Issue Tracker, https://github.com/domdfcoding/rsc-on-this-day/issues
Project-URL: Source Code, https://github.com/domdfcoding/rsc-on-this-day
Project-URL: Documentation, https://rsc-on-this-day.readthedocs.io/en/latest
Platform: Windows
Platform: macOS
Platform: Linux
Classifier: Development Status :: 4 - Beta
Classifier: Environment :: Console
Classifier: License :: OSI Approved :: MIT License
Classifier: Operating System :: OS Independent
Classifier: Programming Language :: Python
Classifier: Programming Language :: Python :: 3 :: Only
Classifier: Programming Language :: Python :: 3.6
Classifier: Programming Language :: Python :: 3.7
Classifier: Programming Language :: Python :: 3.8
Classifier: Programming Language :: Python :: 3.9
Classifier: Programming Language :: Python :: Implementation :: CPython
Requires-Python: >=3.6
Requires-Dist: apeye>=0.5.1
Requires-Dist: beautifulsoup4>=4.7.1
Requires-Dist: click>=7.1.2
Requires-Dist: consolekit>=1.0.0
Requires-Dist: domdf-python-tools>=2.3.0
